{"_path":"/articles/doctl","_dir":"articles","_draft":false,"_partial":false,"_locale":"en","_empty":false,"title":"Exploring the Digital Ocean `doctl` Utility","description":"I recently had the need to spool up a small ephemeral Linux instance, and wanted to try something new by exploring the Digital Ocean doctl command line utility.\nThis proved to be an extremely easy way to configure, create, connect, and destroy a Linux box, and I foresee myself using this service even more in the future.","excerpt":{"type":"root","children":[{"type":"element","tag":"p","props":{},"children":[{"type":"text","value":"I recently had the need to spool up a small ephemeral Linux instance, and wanted to try something new by exploring the Digital Ocean "},{"type":"element","tag":"code-inline","props":{},"children":[{"type":"text","value":"doctl"}]},{"type":"text","value":" command line utility.\nThis proved to be an "},{"type":"element","tag":"em","props":{},"children":[{"type":"text","value":"extremely"}]},{"type":"text","value":" easy way to configure, create, connect, and destroy a Linux box, and I foresee myself using this service even more in the future."}]}]},"date":"2023-01-01","tags":["linux","digital-ocean"],"categories":["linux"],"body":{"type":"root","children":[{"type":"element","tag":"p","props":{},"children":[{"type":"text","value":"I recently had the need to spool up a small ephemeral Linux instance, and wanted to try something new by exploring the Digital Ocean "},{"type":"element","tag":"code-inline","props":{},"children":[{"type":"text","value":"doctl"}]},{"type":"text","value":" command line utility.\nThis proved to be an "},{"type":"element","tag":"em","props":{},"children":[{"type":"text","value":"extremely"}]},{"type":"text","value":" easy way to configure, create, connect, and destroy a Linux box, and I foresee myself using this service even more in the future."}]},{"type":"element","tag":"p","props":{},"children":[{"type":"text","value":"To start things off, I had to install and setup authentication to Digital Ocean. Doing\nthis on my Mac machine, I opted to use "},{"type":"element","tag":"a","props":{"href":"https://brew.sh/","rel":["nofollow"]},"children":[{"type":"text","value":"Homebrew"}]},{"type":"text","value":"."}]},{"type":"element","tag":"code","props":{"code":"# install `doctl`\nbrew install doctl\n\n# setup authentication\ndoctl auth init\n","language":"sh"},"children":[{"type":"element","tag":"pre","props":{},"children":[{"type":"element","tag":"code","props":{"__ignoreMap":""},"children":[{"type":"text","value":"# install `doctl`\nbrew install doctl\n\n# setup authentication\ndoctl auth init\n"}]}]}]},{"type":"element","tag":"p","props":{},"children":[{"type":"text","value":"While the online "},{"type":"element","tag":"a","props":{"href":"https://docs.digitalocean.com/reference/doctl/reference/compute/droplet/create/","rel":["nofollow"]},"children":[{"type":"text","value":"documentation"}]},{"type":"text","value":" is fantastic, I instead found myself mostly referencing the outputs of "},{"type":"element","tag":"code-inline","props":{},"children":[{"type":"text","value":"--help"}]},{"type":"text","value":"."}]},{"type":"element","tag":"code","props":{"code":"doctl compute droplet create --help\n","language":"sh"},"children":[{"type":"element","tag":"pre","props":{},"children":[{"type":"element","tag":"code","props":{"__ignoreMap":""},"children":[{"type":"text","value":"doctl compute droplet create --help\n"}]}]}]},{"type":"element","tag":"p","props":{},"children":[{"type":"text","value":"I had to find the image name of the version of Ubuntu I wanted to install:"}]},{"type":"element","tag":"code","props":{"code":"doctl compute image list --public | grep ubuntu-22\n\n# 118857366    22.04 (LTS) x64    snapshot    Ubuntu    ubuntu-22-04-x64    true    7\n# 119383150    22.10 x64          snapshot    Ubuntu    ubuntu-22-10-x64    true    7\n","language":"sh"},"children":[{"type":"element","tag":"pre","props":{},"children":[{"type":"element","tag":"code","props":{"__ignoreMap":""},"children":[{"type":"text","value":"doctl compute image list --public | grep ubuntu-22\n\n# 118857366    22.04 (LTS) x64    snapshot    Ubuntu    ubuntu-22-04-x64    true    7\n# 119383150    22.10 x64          snapshot    Ubuntu    ubuntu-22-10-x64    true    7\n"}]}]}]},{"type":"element","tag":"p","props":{},"children":[{"type":"text","value":"And also the slug of the compute size:"}]},{"type":"element","tag":"code","props":{"code":"doctl compute size list\n\n# Slug                  Description    Memory    VCPUs    Disk    Price Monthly    Price Hourly\n# s-1vcpu-512mb-10gb    Basic          512       1        10      4.00             0.005950\n# s-1vcpu-1gb           Basic          1024      1        25      6.00             0.008930\n# s-1vcpu-1gb-amd       Basic AMD      1024      1        25      7.00             0.010420\n# s-1vcpu-1gb-intel     Basic Intel    1024      1        25      7.00             0.010420\n# s-1vcpu-2gb           Basic          2048      1        50      12.00            0.017860\n# s-1vcpu-2gb-amd       Basic AMD      2048      1        50      14.00            0.020830\n","language":"sh"},"children":[{"type":"element","tag":"pre","props":{},"children":[{"type":"element","tag":"code","props":{"__ignoreMap":""},"children":[{"type":"text","value":"doctl compute size list\n\n# Slug                  Description    Memory    VCPUs    Disk    Price Monthly    Price Hourly\n# s-1vcpu-512mb-10gb    Basic          512       1        10      4.00             0.005950\n# s-1vcpu-1gb           Basic          1024      1        25      6.00             0.008930\n# s-1vcpu-1gb-amd       Basic AMD      1024      1        25      7.00             0.010420\n# s-1vcpu-1gb-intel     Basic Intel    1024      1        25      7.00             0.010420\n# s-1vcpu-2gb           Basic          2048      1        50      12.00            0.017860\n# s-1vcpu-2gb-amd       Basic AMD      2048      1        50      14.00            0.020830\n"}]}]}]},{"type":"element","tag":"p","props":{},"children":[{"type":"text","value":"I've also configured a few SSH keys with Digital Ocean, and I can have the key (specified by ID) provisioned to the machine using the "},{"type":"element","tag":"code-inline","props":{},"children":[{"type":"text","value":"--ssh-keys"}]},{"type":"text","value":" flag."}]},{"type":"element","tag":"code","props":{"code":"doctl compute ssh-key list\n\n# ID      Name    FingerPrint\n# 1234    mini    <redacted>\n","language":"sh"},"children":[{"type":"element","tag":"pre","props":{},"children":[{"type":"element","tag":"code","props":{"__ignoreMap":""},"children":[{"type":"text","value":"doctl compute ssh-key list\n\n# ID      Name    FingerPrint\n# 1234    mini    <redacted>\n"}]}]}]},{"type":"element","tag":"p","props":{},"children":[{"type":"text","value":"Also, I wanted to install a few packages to the box upon creation, this can be done easily with the "},{"type":"element","tag":"code-inline","props":{},"children":[{"type":"text","value":"--user-data-file"}]},{"type":"text","value":" flag to run an initialization script."}]},{"type":"element","tag":"code","props":{"code":"echo 'apt install -y imagemagick zip' > bootstrap.sh\n","language":"sh"},"children":[{"type":"element","tag":"pre","props":{},"children":[{"type":"element","tag":"code","props":{"__ignoreMap":""},"children":[{"type":"text","value":"echo 'apt install -y imagemagick zip' > bootstrap.sh\n"}]}]}]},{"type":"element","tag":"p","props":{},"children":[{"type":"text","value":"Putting it all together, here is the simple command for creating a small compute instance!"}]},{"type":"element","tag":"code","props":{"code":"doctl compute droplet create \\\n    --image ubuntu-22-10-x64 \\\n    --size s-1vcpu-512mb-10gb \\\n    --region nyc1 \\\n    --ssh-keys 1234 \\\n    --user-data-file boostrap.sh \\\n    ephemeral\n","language":"sh"},"children":[{"type":"element","tag":"pre","props":{},"children":[{"type":"element","tag":"code","props":{"__ignoreMap":""},"children":[{"type":"text","value":"doctl compute droplet create \\\n    --image ubuntu-22-10-x64 \\\n    --size s-1vcpu-512mb-10gb \\\n    --region nyc1 \\\n    --ssh-keys 1234 \\\n    --user-data-file boostrap.sh \\\n    ephemeral\n"}]}]}]},{"type":"element","tag":"p","props":{},"children":[{"type":"text","value":"Finally, I can connect, do my thing, and destroy the instance."}]},{"type":"element","tag":"code","props":{"code":"doctl compute ssh ephemeral\n","language":"sh"},"children":[{"type":"element","tag":"pre","props":{},"children":[{"type":"element","tag":"code","props":{"__ignoreMap":""},"children":[{"type":"text","value":"doctl compute ssh ephemeral\n"}]}]}]},{"type":"element","tag":"code","props":{"code":"doctl compute droplet delete --force ephemeral\n","language":"sh"},"children":[{"type":"element","tag":"pre","props":{},"children":[{"type":"element","tag":"code","props":{"__ignoreMap":""},"children":[{"type":"text","value":"doctl compute droplet delete --force ephemeral\n"}]}]}]},{"type":"element","tag":"p","props":{},"children":[{"type":"text","value":"All-in-all, I was up and running in about 20 minutes. What a handy utility!"}]}],"toc":{"title":"","searchDepth":2,"depth":2,"links":[]}},"_type":"markdown","_id":"content:articles:doctl.md","_source":"content","_file":"articles/doctl.md","_extension":"md"}